easy/__init__.py
easy/data.py
easy/defaults.py
easy/exceptions.py
easy/ez.py
easy/util.py
easy/auth-templates/keycloak.json
easy/auth-templates/login.html
easy_py-0.7.4.dist-info/LICENSE
easy_py-0.7.4.dist-info/METADATA
easy_py-0.7.4.dist-info/WHEEL
easy_py-0.7.4.dist-info/top_level.txt
easy_py-0.7.4.dist-info/RECORD
