Metadata-Version: 2.2
Name: easy-py
Version: 0.7.4
Summary: Python SDK for Easy
Home-page: https://github.com/kspar/easy-py
Author: Kaspar Papli
Author-email: kaspar.papli@gmail.com
License: MIT
Classifier: Programming Language :: Python :: 3
Classifier: License :: OSI Approved :: MIT License
Classifier: Operating System :: OS Independent
Requires-Python: >=3.7
License-File: LICENSE
Requires-Dist: flask~=2.0.3
Requires-Dist: requests<2.32.4,>=2.28.2
Requires-Dist: werkzeug~=2.0.0
Dynamic: author
Dynamic: author-email
Dynamic: classifier
Dynamic: description
Dynamic: description-content-type
Dynamic: home-page
Dynamic: license
Dynamic: requires-dist
Dynamic: requires-python
Dynamic: summary
